moveread/pipelines/correct/__init__.py
moveread/pipelines/correct/__init__.pyi
moveread/pipelines/correct/_api.py
moveread/pipelines/correct/pipeline.py
moveread/pipelines/correct/sdk.py
moveread/pipelines/correct/types.py
moveread/pipelines/correct/util.py
moveread/pipelines/correct/scripts/cli.py
moveread_pipelines_correct-0.1.2.dist-info/METADATA
moveread_pipelines_correct-0.1.2.dist-info/WHEEL
moveread_pipelines_correct-0.1.2.dist-info/entry_points.txt
moveread_pipelines_correct-0.1.2.dist-info/top_level.txt
moveread_pipelines_correct-0.1.2.dist-info/RECORD
