Metadata-Version: 2.1
Name: moveread-pipelines-correct
Version: 0.1.2
Author-email: Marcel Claramunt <marcel@moveread.com>
Project-URL: repo, https://github.com/moveread/pipelines.git
Requires-Python: >=3.10
Requires-Dist: lazy-loader
Requires-Dist: sequence-edits
Requires-Dist: python-kv
Requires-Dist: pipeteer
Requires-Dist: chess-notation
Provides-Extra: run
Requires-Dist: sse-starlette; extra == "run"
Requires-Dist: game-prediction; extra == "run"
Requires-Dist: fastapi; extra == "run"
Requires-Dist: uvicorn; extra == "run"
